netjsonconfig/__init__.py
netjsonconfig/channels.py
netjsonconfig/countries.py
netjsonconfig/exceptions.py
netjsonconfig/schema.py
netjsonconfig/utils.py
netjsonconfig/version.py
netjsonconfig/backends/__init__.py
netjsonconfig/backends/base/__init__.py
netjsonconfig/backends/base/backend.py
netjsonconfig/backends/base/converter.py
netjsonconfig/backends/base/parser.py
netjsonconfig/backends/base/renderer.py
netjsonconfig/backends/openvpn/__init__.py
netjsonconfig/backends/openvpn/converters.py
netjsonconfig/backends/openvpn/openvpn.py
netjsonconfig/backends/openvpn/parser.py
netjsonconfig/backends/openvpn/renderer.py
netjsonconfig/backends/openvpn/schema.py
netjsonconfig/backends/openvpn/templates/openvpn.jinja2
netjsonconfig/backends/openwisp/__init__.py
netjsonconfig/backends/openwisp/openwisp.py
netjsonconfig/backends/openwisp/renderer.py
netjsonconfig/backends/openwisp/schema.py
netjsonconfig/backends/openwisp/templates/install.sh
netjsonconfig/backends/openwisp/templates/openwrt.jinja2
netjsonconfig/backends/openwisp/templates/tc_script.sh
netjsonconfig/backends/openwisp/templates/uninstall.sh
netjsonconfig/backends/openwisp/templates/vpn_script_down.sh
netjsonconfig/backends/openwisp/templates/vpn_script_up.sh
netjsonconfig/backends/openwrt/__init__.py
netjsonconfig/backends/openwrt/openwrt.py
netjsonconfig/backends/openwrt/parser.py
netjsonconfig/backends/openwrt/renderer.py
netjsonconfig/backends/openwrt/schema.py
netjsonconfig/backends/openwrt/timezones.py
netjsonconfig/backends/openwrt/converters/__init__.py
netjsonconfig/backends/openwrt/converters/base.py
netjsonconfig/backends/openwrt/converters/default.py
netjsonconfig/backends/openwrt/converters/general.py
netjsonconfig/backends/openwrt/converters/interfaces.py
netjsonconfig/backends/openwrt/converters/led.py
netjsonconfig/backends/openwrt/converters/ntp.py
netjsonconfig/backends/openwrt/converters/openvpn.py
netjsonconfig/backends/openwrt/converters/radios.py
netjsonconfig-1.2.dist-info/licenses/LICENSE
netjsonconfig-1.2.dist-info/METADATA
netjsonconfig-1.2.dist-info/WHEEL
netjsonconfig-1.2.dist-info/top_level.txt
netjsonconfig-1.2.dist-info/RECORD
