Metadata-Version: 2.4
Name: netjsonconfig
Version: 1.2
Summary: Netjsonconfig is a python library that converts NetJSON DeviceConfiguration objects into real router configurations that can be installed on systems like OpenWRT or OpenWisp Firmware.
Home-page: http://netjsonconfig.openwisp.org
Download-URL: https://github.com/openwisp/netjsonconfig/releases
Author: OpenWISP
Author-email: support@openwisp.io
License: GPL3
Keywords: openwrt,openwisp,netjson,networking
Classifier: Development Status :: 5 - Production/Stable
Classifier: Environment :: Console
Classifier: Intended Audience :: Developers
Classifier: License :: OSI Approved :: GNU General Public License v3 (GPLv3)
Classifier: Operating System :: OS Independent
Classifier: Programming Language :: Python
Classifier: Topic :: System :: Networking
License-File: LICENSE
Requires-Dist: jinja2~=3.1.6
Requires-Dist: jsonschema~=4.25.1
Dynamic: author
Dynamic: author-email
Dynamic: classifier
Dynamic: description
Dynamic: download-url
Dynamic: home-page
Dynamic: keywords
Dynamic: license
Dynamic: license-file
Dynamic: requires-dist
Dynamic: summary
